<Properties StartupConfiguration="{DDFBC18F-9396-3137-9CFE-DEB2CDB74636}|">
  <MonoDevelop.Ide.Workbench ActiveDocument="Assets/Scripts/MovePlayer.cs">
    <Files>
      <File FileName="Assets/Scripts/MovePlayer.cs" Line="31" Column="52" />
    </Files>
    <Pads>
      <Pad Id="ProjectPad">
        <State name="__root__">
          <Node name="Game" expanded="True">
            <Node name="Assets" expanded="True">
              <Node name="Scripts" expanded="True">
                <Node name="MovePlayer.cs" selected="True" />
              </Node>
            </Node>
          </Node>
        </State>
      </Pad>
    </Pads>
  </MonoDevelop.Ide.Workbench>
  <MonoDevelop.Ide.DebuggingService.PinnedWatches />
  <MonoDevelop.Ide.Workspace ActiveConfiguration="Debug" />
  <MonoDevelop.Ide.ItemProperties.Assembly-CSharp PreferredExecutionTarget="f978a5e6-3326-4bf6-804d-76c0e258d785" />
  <MonoDevelop.Ide.DebuggingService.Breakpoints>
    <BreakpointStore />
  </MonoDevelop.Ide.DebuggingService.Breakpoints>
  <MultiItemStartupConfigurations />
</Properties>